relock/__init__.py
relock/crypto/__init__.py
relock/crypto/gcm/__init__.py
relock/crypto/kdm/__init__.py
relock/crypto/kyber/__init__.py
relock/crypto/siv/__init__.py
relock/crypto/xdh/__init__.py
relock/flask/__init__.py
relock/flask/routes.py
relock/flask/context/__init__.py
relock/flask/device/__init__.py
relock/flask/device/login.py
relock/flask/login/__init__.py
relock/flask/login/anonymous.py
relock/nobody/__init__.py
relock/tcp/__init__.py
relock/tcp/base.py
relock/tcp/core.py
relock/tcp/events.py
relock/tcp/pool.py
relock/tcp/socket.py
relock/thread/__init__.py
relock-2.0.1.dist-info/licenses/LICENSE
relock-2.0.1.dist-info/METADATA
relock-2.0.1.dist-info/WHEEL
relock-2.0.1.dist-info/top_level.txt
relock-2.0.1.dist-info/RECORD
