Metadata-Version: 2.4
Name: relock
Version: 2.0.1
Summary: Relock Sentinel - continous passive authentication engine.
Author-email: Marcin Sznyra <marcin@relock.id>
License: # PolyForm Strict License 1.0.0
Project-URL: homepage, https://github.com/relockid/sentinel
Project-URL: repository, https://github.com/relockid/sentinel
Project-URL: docker, https://hub.docker.com/r/relock/sentinel
Classifier: Development Status :: 4 - Beta
Classifier: Programming Language :: Python
Classifier: License :: Other/Proprietary License
Classifier: Operating System :: OS Independent
Requires-Python: >=3.8
License-File: LICENSE
Dynamic: license-file
